rekordbox_bulk_edit/__init__.py
rekordbox_bulk_edit/cli.py
rekordbox_bulk_edit/commands/__init__.py
rekordbox_bulk_edit/commands/convert.py
rekordbox_bulk_edit/commands/read.py
rekordbox_bulk_edit/logger.py
rekordbox_bulk_edit/utils.py
rekordbox_bulk_edit-0.2.7.dist-info/LICENSE
rekordbox_bulk_edit-0.2.7.dist-info/METADATA
rekordbox_bulk_edit-0.2.7.dist-info/WHEEL
rekordbox_bulk_edit-0.2.7.dist-info/entry_points.txt
rekordbox_bulk_edit-0.2.7.dist-info/RECORD
