Metadata-Version: 2.3
Name: rekordbox-bulk-edit
Version: 0.2.7
Summary: Tools for managing and modifying a RekordBox library en-masse
License: MIT
Keywords: rekordbox,dj,music,database,bulk,edit,convert
Author: James Viall
Author-email: jamesviall@pm.me
Requires-Python: >=3.9,<4.0
Classifier: License :: OSI Approved :: MIT License
Classifier: Programming Language :: Python :: 3
Classifier: Programming Language :: Python :: 3.9
Classifier: Programming Language :: Python :: 3.10
Classifier: Programming Language :: Python :: 3.11
Classifier: Programming Language :: Python :: 3.12
Classifier: Programming Language :: Python :: 3.13
Requires-Dist: click (>=8.0.0,<=9.0.0)
Requires-Dist: ffmpeg-python (>=0.2.0)
Requires-Dist: platformdirs (>=4.3.8,<5.0.0)
Requires-Dist: pyrekordbox (>=0.4.3)
Project-URL: Homepage, https://github.com/jviall/rekordbox-bulk-edit
Project-URL: Issues, https://github.com/jviall/rekordbox-bulk-edit/issues
Project-URL: Repository, https://github.com/jviall/rekordbox-bulk-edit
